LICENCE.md
MANIFEST.in
README.rst
setup.cfg
setup.py
jicbioimage/__init__.py
jicbioimage.illustrate.egg-info/PKG-INFO
jicbioimage.illustrate.egg-info/SOURCES.txt
jicbioimage.illustrate.egg-info/dependency_links.txt
jicbioimage.illustrate.egg-info/pbr.json
jicbioimage.illustrate.egg-info/requires.txt
jicbioimage.illustrate.egg-info/top_level.txt
jicbioimage/illustrate/__init__.py
jicbioimage/illustrate/fonts/UbuntuMono-R.ttf
jicbioimage/illustrate/fonts/ubuntu-font-licence-1.0.txt